topsis_riddhi_102483079/__init__.py
topsis_riddhi_102483079/topsis.py
topsis_riddhi_102483079-1.0.0.dist-info/METADATA
topsis_riddhi_102483079-1.0.0.dist-info/WHEEL
topsis_riddhi_102483079-1.0.0.dist-info/entry_points.txt
topsis_riddhi_102483079-1.0.0.dist-info/top_level.txt
topsis_riddhi_102483079-1.0.0.dist-info/RECORD
