Metadata-Version: 2.4
Name: topsis-riddhi-102483079
Version: 1.0.0
Summary: Python package for TOPSIS method
Author: Riddhi
Author-email: riddhi.jain15102004@gmail.com
Requires-Python: >=3.7
Requires-Dist: pandas
Requires-Dist: numpy
Dynamic: author
Dynamic: author-email
Dynamic: description-content-type
Dynamic: requires-dist
Dynamic: requires-python
Dynamic: summary
